[
  {
    "manufacturer": "Hynix",
    "dieName": "5G9T",
    "type": 3,
    "pageDataBytes": 16384,
    "pageRedundantBytes": 2048,
    "frameCount": 16,
    "blockSizePages": 1152,
    "wlPerBlock": 384,
    "wlEncoding": []
  },
  {
    "manufacturer": "Hynix",
    "dieName": "5T0Q",
    "type": 4,
    "pageDataBytes": 16384,
    "pageRedundantBytes": 2560,
    "frameCount": 16,
    "blockSizePages": 1536,
    "wlPerBlock": 384,
    "wlEncoding": [
      15,
      14,
      12,
      8,
      0,
      4,
      5,
      7,
      6,
      2,
      10,
      11,
      3,
      1,
      9,
      13
    ]
  },
  {
    "manufacturer": "Hynix",
    "dieName": "6G9T",
    "type": 3,
    "pageDataBytes": 16384,
    "pageRedundantBytes": 2048,
    "frameCount": 16,
    "blockSizePages": 1536,
    "wlPerBlock": 512,
    "wlEncoding": [
      7,
      3,
      1,
      0,
      2,
      6,
      4,
      5
    ]
  },
  {
    "manufacturer": "Hynix",
    "dieName": "6T0T",
    "type": 3,
    "pageDataBytes": 16384,
    "pageRedundantBytes": 2048,
    "frameCount": 16,
    "blockSizePages": 1536,
    "wlPerBlock": 512,
    "wlEncoding": [
      7,
      3,
      1,
      0,
      2,
      6,
      4,
      5
    ]
  },
  {
    "manufacturer": "Hynix",
    "dieName": "7G9T",
    "type": 3,
    "pageDataBytes": 16384,
    "pageRedundantBytes": 2048,
    "frameCount": 16,
    "blockSizePages": 4224,
    "wlPerBlock": 1408,
    "wlEncoding": [
      7,
      3,
      1,
      0,
      2,
      6,
      4,
      5
    ]
  },
  {
    "manufacturer": "Hynix",
    "dieName": "7T0Q",
    "type": 4,
    "pageDataBytes": 16384,
    "pageRedundantBytes": 2560,
    "frameCount": 16,
    "blockSizePages": 5632,
    "wlPerBlock": 1408,
    "wlEncoding": [
      15,
      14,
      12,
      8,
      0,
      4,
      5,
      7,
      6,
      2,
      10,
      11,
      3,
      1,
      9,
      13
    ]
  },
  {
    "manufacturer": "Hynix",
    "dieName": "8G9T",
    "type": 3,
    "pageDataBytes": 16384,
    "pageRedundantBytes": 2048,
    "frameCount": 16,
    "blockSizePages": 5712,
    "wlPerBlock": 1904,
    "wlEncoding": [
      7,
      3,
      1,
      0,
      2,
      6,
      4,
      5
    ]
  },
  {
    "manufacturer": "Hynix",
    "dieName": "8T0T",
    "type": 3,
    "pageDataBytes": 16384,
    "pageRedundantBytes": 2048,
    "frameCount": 16,
    "blockSizePages": 5712,
    "wlPerBlock": 1904,
    "wlEncoding": [
      7,
      3,
      1,
      0,
      2,
      6,
      4,
      5
    ]
  },
  {
    "manufacturer": "Hynix",
    "dieName": "QDG8D2C",
    "type": 2,
    "pageDataBytes": 16384,
    "pageRedundantBytes": 1280,
    "frameCount": 16,
    "blockSizePages": 576,
    "wlPerBlock": 128,
    "wlEncoding": [
      3,
      2,
      0,
      1
    ]
  },
  {
    "manufacturer": "Hynix",
    "dieName": "QDG8M2C",
    "type": 3,
    "pageDataBytes": 8192,
    "pageRedundantBytes": 1024,
    "frameCount": 8,
    "blockSizePages": 1152,
    "wlPerBlock": 384,
    "wlEncoding": []
  },
  {
    "manufacturer": "Hynix",
    "dieName": "QDG8T2C",
    "type": 2,
    "pageDataBytes": 16384,
    "pageRedundantBytes": 1280,
    "frameCount": 16,
    "blockSizePages": 256,
    "wlPerBlock": 128,
    "wlEncoding": []
  },
  {
    "manufacturer": "Hynix",
    "dieName": "QEG8M2A",
    "type": 3,
    "pageDataBytes": 8192,
    "pageRedundantBytes": 1024,
    "frameCount": 8,
    "blockSizePages": 1728,
    "wlPerBlock": 576,
    "wlEncoding": [
      7,
      3,
      1,
      0,
      2,
      6,
      4,
      5
    ]
  },
  {
    "manufacturer": "Hynix",
    "dieName": "QEG8M2B",
    "type": 3,
    "pageDataBytes": 8192,
    "pageRedundantBytes": 1024,
    "frameCount": 8,
    "blockSizePages": 1152,
    "wlPerBlock": null,
    "wlEncoding": []
  },
  {
    "manufacturer": "Hynix",
    "dieName": "QEG8M3M",
    "type": 3,
    "pageDataBytes": 8192,
    "pageRedundantBytes": 1024,
    "frameCount": 8,
    "blockSizePages": 1152,
    "wlPerBlock": 384,
    "wlEncoding": [
      7,
      3,
      1,
      0,
      2,
      6,
      4,
      5
    ]
  },
  {
    "manufacturer": "Hynix",
    "dieName": "QEM8A1B",
    "type": 2,
    "pageDataBytes": 16384,
    "pageRedundantBytes": 1664,
    "frameCount": 16,
    "blockSizePages": 1216,
    "wlPerBlock": null,
    "wlEncoding": []
  },
  {
    "manufacturer": "Intel",
    "dieName": "B0KB",
    "type": 3,
    "pageDataBytes": 16384,
    "pageRedundantBytes": 2208,
    "frameCount": 16,
    "blockSizePages": 1536,
    "wlPerBlock": 512,
    "wlEncoding": []
  },
  {
    "manufacturer": "Intel",
    "dieName": "B16A",
    "type": 3,
    "pageDataBytes": 16384,
    "pageRedundantBytes": 2208,
    "frameCount": 16,
    "blockSizePages": 2304,
    "wlPerBlock": 768,
    "wlEncoding": []
  },
  {
    "manufacturer": "Intel",
    "dieName": "N18A",
    "type": 4,
    "pageDataBytes": 16384,
    "pageRedundantBytes": 2208,
    "frameCount": 16,
    "blockSizePages": 3072,
    "wlPerBlock": 792,
    "wlEncoding": []
  },
  {
    "manufacturer": "Intel",
    "dieName": "Q4128A",
    "type": 4,
    "pageDataBytes": 16384,
    "pageRedundantBytes": 2208,
    "frameCount": 16,
    "blockSizePages": 9216,
    "wlPerBlock": 2352,
    "wlEncoding": [
      15,
      7,
      3,
      11,
      9,
      1,
      5,
      13,
      12,
      4,
      0,
      8,
      10,
      2,
      6,
      14
    ]
  },
  {
    "manufacturer": "Intel",
    "dieName": "Q4128B",
    "type": 4,
    "pageDataBytes": 16384,
    "pageRedundantBytes": 2208,
    "frameCount": 16,
    "blockSizePages": 9216,
    "wlPerBlock": 2352,
    "wlEncoding": []
  },
  {
    "manufacturer": "Intel",
    "dieName": "Q5171A",
    "type": 4,
    "pageDataBytes": 16384,
    "pageRedundantBytes": 2208,
    "frameCount": 16,
    "blockSizePages": 12288,
    "wlPerBlock": 3120,
    "wlEncoding": [
      15,
      7,
      3,
      11,
      9,
      13,
      5,
      1,
      0,
      8,
      12,
      4,
      6,
      2,
      10,
      14
    ]
  },
  {
    "manufacturer": "Micron",
    "dieName": "B05A",
    "type": 3,
    "pageDataBytes": 16384,
    "pageRedundantBytes": 2208,
    "frameCount": 16,
    "blockSizePages": 768,
    "wlPerBlock": 272,
    "wlEncoding": []
  },
  {
    "manufacturer": "Micron",
    "dieName": "B0KB",
    "type": 3,
    "pageDataBytes": 16384,
    "pageRedundantBytes": 2208,
    "frameCount": 16,
    "blockSizePages": 1536,
    "wlPerBlock": 544,
    "wlEncoding": [
      7,
      3,
      1,
      5,
      4,
      0,
      2,
      6
    ]
  },
  {
    "manufacturer": "Micron",
    "dieName": "B16A",
    "type": 3,
    "pageDataBytes": 16384,
    "pageRedundantBytes": 2208,
    "frameCount": 16,
    "blockSizePages": 2304,
    "wlPerBlock": 792,
    "wlEncoding": [
      7,
      3,
      1,
      5,
      4,
      0,
      2,
      6
    ]
  },
  {
    "manufacturer": "Micron",
    "dieName": "B16C",
    "type": 3,
    "pageDataBytes": 16384,
    "pageRedundantBytes": 2208,
    "frameCount": 16,
    "blockSizePages": 2304,
    "wlPerBlock": 768,
    "wlEncoding": []
  },
  {
    "manufacturer": "Micron",
    "dieName": "B16E",
    "type": 3,
    "pageDataBytes": null,
    "pageRedundantBytes": null,
    "frameCount": 0,
    "blockSizePages": null,
    "wlPerBlock": null,
    "wlEncoding": []
  },
  {
    "manufacturer": "Micron",
    "dieName": "B17A",
    "type": 3,
    "pageDataBytes": 16384,
    "pageRedundantBytes": 2208,
    "frameCount": 16,
    "blockSizePages": 2304,
    "wlPerBlock": 792,
    "wlEncoding": [
      7,
      3,
      1,
      5,
      4,
      0,
      2,
      6
    ]
  },
  {
    "manufacturer": "Micron",
    "dieName": "B27A",
    "type": 3,
    "pageDataBytes": 16384,
    "pageRedundantBytes": 2208,
    "frameCount": 16,
    "blockSizePages": 5184,
    "wlPerBlock": 1782,
    "wlEncoding": [
      7,
      3,
      1,
      5,
      4,
      0,
      2,
      6
    ]
  },
  {
    "manufacturer": "Micron",
    "dieName": "B27B",
    "type": 3,
    "pageDataBytes": 16384,
    "pageRedundantBytes": 2208,
    "frameCount": 16,
    "blockSizePages": 3456,
    "wlPerBlock": 1188,
    "wlEncoding": [
      7,
      3,
      1,
      5,
      4,
      0,
      2,
      6
    ]
  },
  {
    "manufacturer": "Micron",
    "dieName": "B27C",
    "type": 3,
    "pageDataBytes": null,
    "pageRedundantBytes": null,
    "frameCount": 0,
    "blockSizePages": null,
    "wlPerBlock": null,
    "wlEncoding": []
  },
  {
    "manufacturer": "Micron",
    "dieName": "B37R",
    "type": 3,
    "pageDataBytes": 16384,
    "pageRedundantBytes": 1960,
    "frameCount": 16,
    "blockSizePages": 1536,
    "wlPerBlock": 512,
    "wlEncoding": [
      7,
      6,
      4,
      0,
      2,
      3,
      1,
      5
    ]
  },
  {
    "manufacturer": "Micron",
    "dieName": "B47R",
    "type": 3,
    "pageDataBytes": 16384,
    "pageRedundantBytes": 1968,
    "frameCount": 16,
    "blockSizePages": 2112,
    "wlPerBlock": 712,
    "wlEncoding": [
      7,
      6,
      4,
      0,
      2,
      3,
      1,
      5
    ]
  },
  {
    "manufacturer": "Micron",
    "dieName": "B47T",
    "type": 3,
    "pageDataBytes": 16384,
    "pageRedundantBytes": 1968,
    "frameCount": 16,
    "blockSizePages": 2112,
    "wlPerBlock": 712,
    "wlEncoding": [
      7,
      6,
      4,
      0,
      2,
      3,
      1,
      5
    ]
  },
  {
    "manufacturer": "Micron",
    "dieName": "B57T",
    "type": 3,
    "pageDataBytes": 16384,
    "pageRedundantBytes": 1968,
    "frameCount": 16,
    "blockSizePages": 2784,
    "wlPerBlock": 936,
    "wlEncoding": [
      7,
      6,
      4,
      0,
      2,
      3,
      1,
      5
    ]
  },
  {
    "manufacturer": "Micron",
    "dieName": "B58R",
    "type": 3,
    "pageDataBytes": 16384,
    "pageRedundantBytes": 1968,
    "frameCount": 16,
    "blockSizePages": 2784,
    "wlPerBlock": 936,
    "wlEncoding": []
  },
  {
    "manufacturer": "Micron",
    "dieName": "B68S",
    "type": 3,
    "pageDataBytes": null,
    "pageRedundantBytes": null,
    "frameCount": 0,
    "blockSizePages": null,
    "wlPerBlock": null,
    "wlEncoding": []
  },
  {
    "manufacturer": "Micron",
    "dieName": "L04A",
    "type": 2,
    "pageDataBytes": 16384,
    "pageRedundantBytes": 2208,
    "frameCount": 16,
    "blockSizePages": 512,
    "wlPerBlock": 272,
    "wlEncoding": [
      3,
      1,
      0,
      2
    ]
  },
  {
    "manufacturer": "Micron",
    "dieName": "L05B",
    "type": 2,
    "pageDataBytes": 16384,
    "pageRedundantBytes": 2208,
    "frameCount": 16,
    "blockSizePages": 512,
    "wlPerBlock": null,
    "wlEncoding": []
  },
  {
    "manufacturer": "Micron",
    "dieName": "L06B",
    "type": 2,
    "pageDataBytes": 16384,
    "pageRedundantBytes": 2208,
    "frameCount": 16,
    "blockSizePages": 1024,
    "wlPerBlock": 544,
    "wlEncoding": [
      7,
      3,
      1,
      5,
      4,
      0,
      2,
      6
    ]
  },
  {
    "manufacturer": "Micron",
    "dieName": "M26A",
    "type": 1,
    "pageDataBytes": 16384,
    "pageRedundantBytes": 2208,
    "frameCount": 16,
    "blockSizePages": 1152,
    "wlPerBlock": 1152,
    "wlEncoding": []
  },
  {
    "manufacturer": "Micron",
    "dieName": "N18A",
    "type": 4,
    "pageDataBytes": 16384,
    "pageRedundantBytes": 2208,
    "frameCount": 16,
    "blockSizePages": 3072,
    "wlPerBlock": 792,
    "wlEncoding": []
  },
  {
    "manufacturer": "Micron",
    "dieName": "N28A",
    "type": 4,
    "pageDataBytes": 16384,
    "pageRedundantBytes": 2208,
    "frameCount": 16,
    "blockSizePages": 4608,
    "wlPerBlock": 1188,
    "wlEncoding": []
  },
  {
    "manufacturer": "Micron",
    "dieName": "N48R",
    "type": 4,
    "pageDataBytes": 16384,
    "pageRedundantBytes": 1968,
    "frameCount": 16,
    "blockSizePages": 2816,
    "wlPerBlock": 712,
    "wlEncoding": [
      15,
      14,
      10,
      8,
      9,
      1,
      0,
      2,
      6,
      4,
      12,
      13,
      5,
      7,
      3,
      11
    ]
  },
  {
    "manufacturer": "Micron",
    "dieName": "N58R",
    "type": 4,
    "pageDataBytes": 16384,
    "pageRedundantBytes": 2608,
    "frameCount": 16,
    "blockSizePages": 3712,
    "wlPerBlock": 936,
    "wlEncoding": []
  },
  {
    "manufacturer": "Samsung",
    "dieName": "3KGC-J",
    "type": 4,
    "pageDataBytes": 16384,
    "pageRedundantBytes": 2048,
    "frameCount": 16,
    "blockSizePages": 5632,
    "wlPerBlock": 1408,
    "wlEncoding": [
      15,
      14,
      10,
      8,
      9,
      1,
      0,
      2,
      6,
      4,
      12,
      13,
      5,
      7,
      3,
      11
    ]
  },
  {
    "manufacturer": "Samsung",
    "dieName": "AFGA-S",
    "type": 3,
    "pageDataBytes": 16384,
    "pageRedundantBytes": 2048,
    "frameCount": 16,
    "blockSizePages": 768,
    "wlPerBlock": 264,
    "wlEncoding": []
  },
  {
    "manufacturer": "Samsung",
    "dieName": "AFGB-J",
    "type": 3,
    "pageDataBytes": 16384,
    "pageRedundantBytes": 2048,
    "frameCount": 16,
    "blockSizePages": 1104,
    "wlPerBlock": 376,
    "wlEncoding": [
      7,
      6,
      4,
      0,
      2,
      3,
      1,
      5
    ]
  },
  {
    "manufacturer": "Samsung",
    "dieName": "AFGB-S",
    "type": 3,
    "pageDataBytes": 16384,
    "pageRedundantBytes": 2048,
    "frameCount": 16,
    "blockSizePages": 1104,
    "wlPerBlock": 376,
    "wlEncoding": [
      7,
      6,
      4,
      0,
      2,
      3,
      1,
      5
    ]
  },
  {
    "manufacturer": "Samsung",
    "dieName": "AFGC-H",
    "type": 3,
    "pageDataBytes": 16384,
    "pageRedundantBytes": 2048,
    "frameCount": 16,
    "blockSizePages": 3096,
    "wlPerBlock": 1040,
    "wlEncoding": [
      7,
      6,
      4,
      0,
      2,
      3,
      1,
      5
    ]
  },
  {
    "manufacturer": "Samsung",
    "dieName": "AFGC-J",
    "type": 3,
    "pageDataBytes": 16384,
    "pageRedundantBytes": 2048,
    "frameCount": 16,
    "blockSizePages": 3096,
    "wlPerBlock": 1040,
    "wlEncoding": [
      7,
      6,
      4,
      0,
      2,
      3,
      1,
      5
    ]
  },
  {
    "manufacturer": "Samsung",
    "dieName": "AFGM-S",
    "type": 3,
    "pageDataBytes": 16384,
    "pageRedundantBytes": 2048,
    "frameCount": 16,
    "blockSizePages": 576,
    "wlPerBlock": 200,
    "wlEncoding": []
  },
  {
    "manufacturer": "Samsung",
    "dieName": "AHGA-J",
    "type": 3,
    "pageDataBytes": 16384,
    "pageRedundantBytes": 2048,
    "frameCount": 16,
    "blockSizePages": 1104,
    "wlPerBlock": 376,
    "wlEncoding": [
      7,
      6,
      4,
      0,
      2,
      3,
      1,
      5
    ]
  },
  {
    "manufacturer": "Samsung",
    "dieName": "AHGA-S",
    "type": 3,
    "pageDataBytes": 16384,
    "pageRedundantBytes": 2048,
    "frameCount": 16,
    "blockSizePages": 1104,
    "wlPerBlock": 376,
    "wlEncoding": [
      7,
      6,
      4,
      0,
      2,
      3,
      1,
      5
    ]
  },
  {
    "manufacturer": "Samsung",
    "dieName": "AHGB-H",
    "type": 3,
    "pageDataBytes": 16384,
    "pageRedundantBytes": 2048,
    "frameCount": 16,
    "blockSizePages": 3096,
    "wlPerBlock": 1040,
    "wlEncoding": [
      7,
      6,
      4,
      0,
      2,
      3,
      1,
      5
    ]
  },
  {
    "manufacturer": "Samsung",
    "dieName": "AHGB-J",
    "type": 3,
    "pageDataBytes": 16384,
    "pageRedundantBytes": 2048,
    "frameCount": 16,
    "blockSizePages": 3096,
    "wlPerBlock": 1040,
    "wlEncoding": [
      7,
      6,
      4,
      0,
      2,
      3,
      1,
      5
    ]
  },
  {
    "manufacturer": "Samsung",
    "dieName": "AHGD-J",
    "type": 3,
    "pageDataBytes": 16384,
    "pageRedundantBytes": 2048,
    "frameCount": 16,
    "blockSizePages": 3168,
    "wlPerBlock": 1416,
    "wlEncoding": []
  },
  {
    "manufacturer": "Samsung",
    "dieName": "AHGE-J",
    "type": 3,
    "pageDataBytes": 16384,
    "pageRedundantBytes": 2048,
    "frameCount": 16,
    "blockSizePages": 3208,
    "wlPerBlock": 1080,
    "wlEncoding": []
  },
  {
    "manufacturer": "Samsung",
    "dieName": "AHGM-J",
    "type": 3,
    "pageDataBytes": 16384,
    "pageRedundantBytes": 2048,
    "frameCount": 16,
    "blockSizePages": 768,
    "wlPerBlock": 264,
    "wlEncoding": []
  },
  {
    "manufacturer": "Samsung",
    "dieName": "AKGD-J",
    "type": 3,
    "pageDataBytes": 16384,
    "pageRedundantBytes": 2048,
    "frameCount": 16,
    "blockSizePages": 4248,
    "wlPerBlock": 1428,
    "wlEncoding": [
      7,
      6,
      4,
      0,
      2,
      3,
      1,
      5
    ]
  },
  {
    "manufacturer": "Samsung",
    "dieName": "FCGM-J",
    "type": 1,
    "pageDataBytes": 2048,
    "pageRedundantBytes": 192,
    "frameCount": 2,
    "blockSizePages": 768,
    "wlPerBlock": 768,
    "wlEncoding": []
  },
  {
    "manufacturer": "Samsung",
    "dieName": "GCGF-U",
    "type": 2,
    "pageDataBytes": 16384,
    "pageRedundantBytes": 1536,
    "frameCount": 16,
    "blockSizePages": 792,
    "wlPerBlock": 400,
    "wlEncoding": [
      3,
      1,
      0,
      2
    ]
  },
  {
    "manufacturer": "Samsung",
    "dieName": "GFGA-H",
    "type": 2,
    "pageDataBytes": null,
    "pageRedundantBytes": null,
    "frameCount": 0,
    "blockSizePages": null,
    "wlPerBlock": null,
    "wlEncoding": []
  },
  {
    "manufacturer": "Samsung",
    "dieName": "GHGM-S",
    "type": 2,
    "pageDataBytes": 16384,
    "pageRedundantBytes": 1536,
    "frameCount": 16,
    "blockSizePages": 384,
    "wlPerBlock": 200,
    "wlEncoding": []
  },
  {
    "manufacturer": "SanDisk",
    "dieName": "G7T23",
    "type": 3,
    "pageDataBytes": 16384,
    "pageRedundantBytes": 1952,
    "frameCount": 16,
    "blockSizePages": 768,
    "wlPerBlock": 256,
    "wlEncoding": [
      7,
      6,
      4,
      0,
      2,
      3,
      1,
      5
    ]
  },
  {
    "manufacturer": "SanDisk",
    "dieName": "G8F24",
    "type": 4,
    "pageDataBytes": 16384,
    "pageRedundantBytes": 2592,
    "frameCount": 16,
    "blockSizePages": 1536,
    "wlPerBlock": 384,
    "wlEncoding": []
  },
  {
    "manufacturer": "SanDisk",
    "dieName": "G8T22",
    "type": 3,
    "pageDataBytes": 16384,
    "pageRedundantBytes": 1952,
    "frameCount": 16,
    "blockSizePages": 576,
    "wlPerBlock": 192,
    "wlEncoding": [
      7,
      6,
      4,
      0,
      2,
      3,
      1,
      5
    ]
  },
  {
    "manufacturer": "SanDisk",
    "dieName": "G8X23",
    "type": 3,
    "pageDataBytes": 16384,
    "pageRedundantBytes": 1952,
    "frameCount": 16,
    "blockSizePages": 768,
    "wlPerBlock": 256,
    "wlEncoding": [
      7,
      6,
      4,
      0,
      2,
      3,
      1,
      5
    ]
  },
  {
    "manufacturer": "SanDisk",
    "dieName": "G8X24",
    "type": 3,
    "pageDataBytes": 16384,
    "pageRedundantBytes": 1952,
    "frameCount": 16,
    "blockSizePages": 1152,
    "wlPerBlock": 384,
    "wlEncoding": [
      7,
      6,
      4,
      0,
      2,
      3,
      1,
      5
    ]
  },
  {
    "manufacturer": "SanDisk",
    "dieName": "G9T23",
    "type": 3,
    "pageDataBytes": 16384,
    "pageRedundantBytes": 1952,
    "frameCount": 16,
    "blockSizePages": 768,
    "wlPerBlock": 256,
    "wlEncoding": []
  },
  {
    "manufacturer": "SanDisk",
    "dieName": "G9T24",
    "type": 3,
    "pageDataBytes": 16384,
    "pageRedundantBytes": 1952,
    "frameCount": 16,
    "blockSizePages": 1152,
    "wlPerBlock": 384,
    "wlEncoding": []
  },
  {
    "manufacturer": "SanDisk",
    "dieName": "G9T24.5",
    "type": 3,
    "pageDataBytes": 16384,
    "pageRedundantBytes": 1952,
    "frameCount": 16,
    "blockSizePages": 1152,
    "wlPerBlock": 384,
    "wlEncoding": []
  },
  {
    "manufacturer": "SanDisk",
    "dieName": "G9T25",
    "type": 3,
    "pageDataBytes": 16384,
    "pageRedundantBytes": 1952,
    "frameCount": 16,
    "blockSizePages": 1344,
    "wlPerBlock": 448,
    "wlEncoding": []
  },
  {
    "manufacturer": "SanDisk",
    "dieName": "T0F25",
    "type": 4,
    "pageDataBytes": 16384,
    "pageRedundantBytes": 2592,
    "frameCount": 16,
    "blockSizePages": 1792,
    "wlPerBlock": 448,
    "wlEncoding": [
      15,
      14,
      12,
      13,
      9,
      1,
      0,
      8,
      10,
      2,
      6,
      4,
      5,
      7,
      3,
      11
    ]
  },
  {
    "manufacturer": "SanDisk",
    "dieName": "T0F48",
    "type": 4,
    "pageDataBytes": 16384,
    "pageRedundantBytes": 2600,
    "frameCount": 16,
    "blockSizePages": 4360,
    "wlPerBlock": 1090,
    "wlEncoding": []
  },
  {
    "manufacturer": "SanDisk",
    "dieName": "T0T46",
    "type": 3,
    "pageDataBytes": 16384,
    "pageRedundantBytes": 1952,
    "frameCount": 16,
    "blockSizePages": 2430,
    "wlPerBlock": 810,
    "wlEncoding": [
      7,
      6,
      4,
      0,
      2,
      3,
      1,
      5
    ]
  },
  {
    "manufacturer": "SanDisk",
    "dieName": "T0T48",
    "type": 3,
    "pageDataBytes": 16384,
    "pageRedundantBytes": 1952,
    "frameCount": 16,
    "blockSizePages": 3270,
    "wlPerBlock": 1090,
    "wlEncoding": []
  },
  {
    "manufacturer": "Toshiba",
    "dieName": "G0Y48",
    "type": 3,
    "pageDataBytes": 16384,
    "pageRedundantBytes": 1952,
    "frameCount": 16,
    "blockSizePages": 3270,
    "wlPerBlock": 1090,
    "wlEncoding": []
  },
  {
    "manufacturer": "Toshiba",
    "dieName": "G7D22",
    "type": 2,
    "pageDataBytes": 16384,
    "pageRedundantBytes": 1280,
    "frameCount": 16,
    "blockSizePages": 384,
    "wlPerBlock": 192,
    "wlEncoding": [
      3,
      1,
      0,
      2
    ]
  },
  {
    "manufacturer": "Toshiba",
    "dieName": "G7T23",
    "type": 3,
    "pageDataBytes": 16384,
    "pageRedundantBytes": 1952,
    "frameCount": 16,
    "blockSizePages": 768,
    "wlPerBlock": 256,
    "wlEncoding": [
      7,
      6,
      4,
      0,
      2,
      3,
      1,
      5
    ]
  },
  {
    "manufacturer": "Toshiba",
    "dieName": "G8F24",
    "type": 4,
    "pageDataBytes": 16384,
    "pageRedundantBytes": 2592,
    "frameCount": 16,
    "blockSizePages": 1536,
    "wlPerBlock": 384,
    "wlEncoding": []
  },
  {
    "manufacturer": "Toshiba",
    "dieName": "G8T22",
    "type": 3,
    "pageDataBytes": 16384,
    "pageRedundantBytes": 1952,
    "frameCount": 16,
    "blockSizePages": 576,
    "wlPerBlock": 192,
    "wlEncoding": [
      7,
      6,
      4,
      0,
      2,
      3,
      1,
      5
    ]
  },
  {
    "manufacturer": "Toshiba",
    "dieName": "G8T23",
    "type": 3,
    "pageDataBytes": 16384,
    "pageRedundantBytes": 1952,
    "frameCount": 16,
    "blockSizePages": 768,
    "wlPerBlock": 256,
    "wlEncoding": [
      7,
      6,
      4,
      0,
      2,
      3,
      1,
      5
    ]
  },
  {
    "manufacturer": "Toshiba",
    "dieName": "G8W23",
    "type": 3,
    "pageDataBytes": 16384,
    "pageRedundantBytes": 1952,
    "frameCount": 16,
    "blockSizePages": 768,
    "wlPerBlock": 256,
    "wlEncoding": [
      7,
      6,
      4,
      0,
      2,
      3,
      1,
      5
    ]
  },
  {
    "manufacturer": "Toshiba",
    "dieName": "G9T24",
    "type": 3,
    "pageDataBytes": 16384,
    "pageRedundantBytes": 1952,
    "frameCount": 16,
    "blockSizePages": 1152,
    "wlPerBlock": 384,
    "wlEncoding": [
      7,
      6,
      4,
      0,
      2,
      3,
      1,
      5
    ]
  },
  {
    "manufacturer": "Toshiba",
    "dieName": "G9T25",
    "type": 3,
    "pageDataBytes": 16384,
    "pageRedundantBytes": 1952,
    "frameCount": 16,
    "blockSizePages": 1344,
    "wlPerBlock": 448,
    "wlEncoding": []
  },
  {
    "manufacturer": "Toshiba",
    "dieName": "G9Y45",
    "type": 3,
    "pageDataBytes": 16384,
    "pageRedundantBytes": 1952,
    "frameCount": 16,
    "blockSizePages": 1344,
    "wlPerBlock": 448,
    "wlEncoding": []
  },
  {
    "manufacturer": "Toshiba",
    "dieName": "GF23B",
    "type": 4,
    "pageDataBytes": 16384,
    "pageRedundantBytes": 1956,
    "frameCount": 16,
    "blockSizePages": 1024,
    "wlPerBlock": 256,
    "wlEncoding": []
  },
  {
    "manufacturer": "YMTC",
    "dieName": "A06M1(X0-A030)",
    "type": 2,
    "pageDataBytes": 16384,
    "pageRedundantBytes": 2208,
    "frameCount": 16,
    "blockSizePages": 256,
    "wlPerBlock": 128,
    "wlEncoding": [
      3,
      2,
      0,
      1
    ]
  },
  {
    "manufacturer": "YMTC",
    "dieName": "X1-9050(Client)",
    "type": 3,
    "pageDataBytes": 16384,
    "pageRedundantBytes": 2048,
    "frameCount": 16,
    "blockSizePages": 1152,
    "wlPerBlock": 384,
    "wlEncoding": [
      7,
      6,
      4,
      0,
      2,
      3,
      1,
      5
    ]
  },
  {
    "manufacturer": "YMTC",
    "dieName": "X1-9050(Consumer)",
    "type": 3,
    "pageDataBytes": 16384,
    "pageRedundantBytes": 2048,
    "frameCount": 16,
    "blockSizePages": 1152,
    "wlPerBlock": 384,
    "wlEncoding": [
      7,
      6,
      4,
      0,
      2,
      3,
      1,
      5
    ]
  },
  {
    "manufacturer": "YMTC",
    "dieName": "X2-6070",
    "type": 4,
    "pageDataBytes": 16384,
    "pageRedundantBytes": 2048,
    "frameCount": 16,
    "blockSizePages": 3048,
    "wlPerBlock": 768,
    "wlEncoding": [
      15,
      7,
      6,
      4,
      12,
      8,
      0,
      2,
      3,
      1,
      5,
      13,
      9,
      11,
      10,
      14
    ]
  },
  {
    "manufacturer": "YMTC",
    "dieName": "X2-9060",
    "type": 3,
    "pageDataBytes": 16384,
    "pageRedundantBytes": 2048,
    "frameCount": 16,
    "blockSizePages": 2304,
    "wlPerBlock": 768,
    "wlEncoding": [
      7,
      6,
      4,
      0,
      2,
      3,
      1,
      5
    ]
  },
  {
    "manufacturer": "YMTC",
    "dieName": "X3-6070",
    "type": 4,
    "pageDataBytes": 16384,
    "pageRedundantBytes": 2432,
    "frameCount": 16,
    "blockSizePages": 5544,
    "wlPerBlock": 1391,
    "wlEncoding": []
  },
  {
    "manufacturer": "YMTC",
    "dieName": "X3-9060",
    "type": 3,
    "pageDataBytes": 16384,
    "pageRedundantBytes": 2048,
    "frameCount": 16,
    "blockSizePages": 2304,
    "wlPerBlock": 768,
    "wlEncoding": [
      7,
      6,
      4,
      0,
      2,
      3,
      1,
      5
    ]
  },
  {
    "manufacturer": "YMTC",
    "dieName": "X3-9070",
    "type": 3,
    "pageDataBytes": 16384,
    "pageRedundantBytes": 1984,
    "frameCount": 16,
    "blockSizePages": 4176,
    "wlPerBlock": 1392,
    "wlEncoding": [
      7,
      6,
      4,
      0,
      2,
      3,
      1,
      5
    ]
  },
  {
    "manufacturer": "YMTC",
    "dieName": "X4-6080",
    "type": 4,
    "pageDataBytes": null,
    "pageRedundantBytes": null,
    "frameCount": 0,
    "blockSizePages": null,
    "wlPerBlock": null,
    "wlEncoding": []
  },
  {
    "manufacturer": "YMTC",
    "dieName": "X4-9060(Client)",
    "type": 3,
    "pageDataBytes": 16384,
    "pageRedundantBytes": 2048,
    "frameCount": 16,
    "blockSizePages": 4800,
    "wlPerBlock": 1600,
    "wlEncoding": [
      7,
      6,
      4,
      0,
      2,
      3,
      1,
      5
    ]
  },
  {
    "manufacturer": "YMTC",
    "dieName": "X4-9060(M-Lite)",
    "type": 3,
    "pageDataBytes": 16384,
    "pageRedundantBytes": 2048,
    "frameCount": 16,
    "blockSizePages": 4800,
    "wlPerBlock": 1600,
    "wlEncoding": [
      7,
      6,
      4,
      0,
      2,
      3,
      1,
      5
    ]
  },
  {
    "manufacturer": "YMTC",
    "dieName": "X4-9070",
    "type": 3,
    "pageDataBytes": 16384,
    "pageRedundantBytes": 2048,
    "frameCount": 16,
    "blockSizePages": 6408,
    "wlPerBlock": 2136,
    "wlEncoding": []
  }
]
